{
  "id": "v99",
  "content_type": "video",
  "course": "Intro to Financial Accounting",
  "topic": "Cash flow statement",
  "subtopic": "Comprehensive Review",
  "tags": [
    "cash-flow-statement",
    "financial-statements",
    "financial-accounting"
  ],
  "title": "Cash flow statement for beginners (step-by-step tutorial)",
  "summary": "Step-by-step tutorial on preparing a cash flow statement using operating, investing, and financing activity sections.",
  "thumbnail": "https://i.ytimg.com/vi/cERimSxGx24/hqdefault.jpg",
  "youtube_url": "https://www.youtube.com/watch?v=cERimSxGx24"
}
